xdgenvpy-stubs/METADATA.toml
xdgenvpy-stubs/__init__.pyi
xdgenvpy-stubs/_defaults.pyi
xdgenvpy-stubs/py.typed
xdgenvpy-stubs/xdgenv.pyi
types_xdgenvpy-2.4.0.20240905.dist-info/METADATA
types_xdgenvpy-2.4.0.20240905.dist-info/WHEEL
types_xdgenvpy-2.4.0.20240905.dist-info/top_level.txt
types_xdgenvpy-2.4.0.20240905.dist-info/RECORD
